pybenchmarker/_BenchmarkN.py
pybenchmarker/__init__.py
pybenchmarker/_progress.py
pybenchmarker-0.1.0.dist-info/LICENSE
pybenchmarker-0.1.0.dist-info/METADATA
pybenchmarker-0.1.0.dist-info/WHEEL
pybenchmarker-0.1.0.dist-info/top_level.txt
pybenchmarker-0.1.0.dist-info/RECORD
