Metadata-Version: 2.1
Name: pybenchmarker
Version: 0.1.0
Summary: Python module to benchmark and compare functions
Author: Owain Davies
License: MIT License
Project-URL: homepage, https://github.com/OTheDev/pybenchmarker
Classifier: Programming Language :: Python :: 3
Classifier: License :: OSI Approved :: MIT License
Classifier: Operating System :: OS Independent
Classifier: Intended Audience :: Developers
Requires-Python: >=3.10.1
License-File: LICENSE
Requires-Dist: matplotlib (>=3.6.0)
